Metadata-Version: 1.0
Name: iati2hxl
Version: 0.2
Summary: Convert IATI to HXL
Home-page: UNKNOWN
Author: David Megginson
Author-email: contact@megginson.com
License: UNKNOWN
Platform: UNKNOWN
